odoo/addons/report_hotel_restaurant/README.rst
odoo/addons/report_hotel_restaurant/__init__.py
odoo/addons/report_hotel_restaurant/__manifest__.py
odoo/addons/report_hotel_restaurant/LICENSE/LICENSE
odoo/addons/report_hotel_restaurant/i18n/es.po
odoo/addons/report_hotel_restaurant/i18n/fr_BE.po
odoo/addons/report_hotel_restaurant/i18n/report_hotel_restaurant.pot
odoo/addons/report_hotel_restaurant/i18n/sv.po
odoo/addons/report_hotel_restaurant/models/__init__.py
odoo/addons/report_hotel_restaurant/models/report_hotel_restaurant.py
odoo/addons/report_hotel_restaurant/security/ir.model.access.csv
odoo/addons/report_hotel_restaurant/static/description/icon.png
odoo/addons/report_hotel_restaurant/static/description/sbrest.png
odoo/addons/report_hotel_restaurant/static/description/serpent.png
odoo/addons/report_hotel_restaurant/views/report_hotel_restaurant_view.xml
odoo13_addon_report_hotel_restaurant-13.0.1.0.1.dev6.dist-info/METADATA
odoo13_addon_report_hotel_restaurant-13.0.1.0.1.dev6.dist-info/WHEEL
odoo13_addon_report_hotel_restaurant-13.0.1.0.1.dev6.dist-info/top_level.txt
odoo13_addon_report_hotel_restaurant-13.0.1.0.1.dev6.dist-info/RECORD
