Metadata-Version: 2.1
Name: odoo13-addon-report-hotel-restaurant
Version: 13.0.1.0.1.dev6
Summary: Restaurant Management - Reporting
Home-page: https://github.com/OCA/vertical-hotel
Author: Odoo Community Association (OCA), Serpent Consulting Services Pvt. Ltd., Odoo S.A.
Author-email: support@odoo-community.org
License: AGPL-3
Platform: UNKNOWN
Classifier: Programming Language :: Python
Classifier: Framework :: Odoo
Classifier: License :: OSI Approved :: GNU Affero General Public License v3
Requires-Python: >=3.5
Requires-Dist: odoo13-addon-hotel-restaurant
Requires-Dist: odoo13-addon-report-hotel-reservation
Requires-Dist: odoo (<13.1dev,>=13.0a)
